<?xml version="1.0" encoding="UTF-8" ?>
<!DOCTYPE struts PUBLIC
    "-//Apache Software Foundation//DTD Struts Configuration 2.0//EN"
    "http://struts.apache.org/dtds/struts-2.0.dtd">

<struts>


	<constant name="struts.i18n.encoding" value="ISO-8859-1" />
	<constant name="struts.enable.DynamicMethodInvocation" value="false" />
	<constant name="struts.devMode" value="false" />
	<constant name="struts.custom.i18n.resources" value="ApplicationResources,FrameworkResources" />
	<constant name="struts.mapper.action.prefix.enabled" value="true" />

	<package name="fwk" extends="tiles-default">
<!-- 
		<result-types>
			<result-type name="jasper"
				class="org.apache.struts2.views.jasperreports.JasperReportsResult" />
			<result-type name="json" class="org.apache.struts2.json.JSONResult" />
		</result-types>
 -->
		<interceptors>
			<interceptor name="exceptionHandler"
				class="com.map.j2ee.struts2.interceptor.ExceptionHandlerInterceptor" />

			<interceptor-stack name="defaultFrameworkStack">
				<interceptor-ref name="exceptionHandler">
					<param name="logLevel">DEBUG</param>
				</interceptor-ref>
				<interceptor-ref name="alias" />
				<interceptor-ref name="servletConfig" />
				<interceptor-ref name="i18n" />
				<interceptor-ref name="chain" />
				<interceptor-ref name="checkbox"/>
				<interceptor-ref name="fileUpload">
					<param name="maximumSize">1024000</param>
					<param name="allowedTypes">image/jpeg,image/gif,image/png,text/plain,application/pdf,application/msword</param>
				</interceptor-ref>
				<interceptor-ref name="params">
					<!-- Excluimos el parametro que forma el display tag para paginar -->
					<param name="excludeParams">d-49653-p</param>

				</interceptor-ref>
				<interceptor-ref name="validation" />
				<interceptor-ref name="prepare" />
				<interceptor-ref name="workflow" />
				<interceptor-ref name="staticParams" />
			</interceptor-stack>
        

            <interceptor-stack name="storeStack">
                <interceptor-ref name="defaultStack"/>
                <interceptor-ref name="store">
					<param name="operationMode">STORE</param>
				</interceptor-ref>
            </interceptor-stack>

            <interceptor-stack name="retrieveStack">
                <interceptor-ref name="defaultStack"/>
                <interceptor-ref name="store">
					<param name="operationMode">RETRIEVE</param>
				</interceptor-ref>
            </interceptor-stack>

     
		</interceptors>
		<default-interceptor-ref name="defaultFrameworkStack"></default-interceptor-ref>
		<global-results>
			<result type="tiles" name="error">pages.fwkerror</result>
			<result type="tiles" name="fwkerror">pages.fwkerror</result>
			<result type="tiles" name="securityerror">pages.securityerror</result>
		</global-results>
		<global-exception-mappings>
			<exception-mapping result="error" exception="java.lang.Exception"></exception-mapping>
			<exception-mapping result="error"
				exception="com.map.j2ee.exceptions.BaseException"></exception-mapping>
			<exception-mapping result="error" exception="com.map.j2ee.exceptions.BusinessException"/>
		</global-exception-mappings>

	</package>


	<package name="plataformamensajeriaapp2" extends="fwk">

		<action name="pool" class="es.mpr.template.pool.poolObject"
			method="obtenerPool">
			<result type="tiles">pages.pool</result>
		</action>
		<action name="infoHome" class="homeAction" method="infoHome">	<!-- SE USA -->		
			<result type="tiles">site.index.page</result>
			<result name="noUser" type="tiles">pages.nouser</result>
			<result name="error" type="tiles">site.index.page</result>
		</action>
		<action name="home" class="logonAction" method="permisosMenu"><!-- SE USA -->
			<result name="success" type="redirectAction">
				<param name="actionName">infoHome</param>
				<param name="parse">true</param> 
			</result>
			<result name="error" type="tiles">pages.nouser_sistema</result>
		</action>

		<action name="homecert" class="logonAction" method="permisosMenu"><!-- SE USA -->
			<result type="tiles">site.index.page</result>
			<result name="error" type="tiles">pages.nouser</result>
		</action>

		<action name="contacto" class="mailSender" method="newMail">
			<result name="success" type="tiles">pages.mail.sender</result>
			<result name="noUser" type="tiles">pages.nouser</result>
		</action>

		<action name="enviar" class="mailSender" method="send">
			<result name="input" type="tiles">pages.mail.sender</result>
			<result name="success" type="tiles">site.index.page</result>
			<result name="noUser" type="tiles">pages.nouser</result>
		</action>

		<!-- Menu administracion -->
		<action name="adminUsuarios" class="gestorUsuarios" method="newSearch">
			<result name="success" type="tiles">pages.searchUsuario</result>
			<result name="noUser" type="tiles">pages.nouser</result>
		</action>
		
		<action name="adminNuevoUsuario" class="gestorUsuarios" method="create">
			<result type="tiles">pages.createUsuario</result>
			<result name="noUser" type="tiles">pages.nouser</result>
		</action>

		<action name="adminEditarUsuario" class="gestorUsuarios"
			method="edit">
			<result type="tiles">pages.mantUsuario</result>
			<result name="noUser" type="tiles">pages.nouser</result>
		</action>

		<action name="adminVerUsuario" class="gestorUsuarios" method="editSelf">
			<result type="tiles">pages.consUsuario</result>
			<result name="noUser" type="tiles">pages.nouser</result>
		</action>

		<action name="adminCambiarPasswordUsuario" class="gestorUsuarios"
			method="editPassword">
			<result name="input" type="tiles">pages.mantUsuario</result>
			<result type="tiles">pages.cambiarPasswordUsuario</result>
			<result name="noUser" type="tiles">pages.nouser</result>
		</action>

		<action name="adminCambioPasswordUsuario" class="gestorUsuarios"
			method="savePassword">
			<result name="input" type="tiles">pages.cambiarPasswordUsuario
			</result>
			<result type="chain">adminVerUsuario</result>
			<result name="noUser" type="tiles">pages.nouser</result>
		</action>

		<action name="adminBuscarUsuarios" class="gestorUsuarios"
			method="search">
			<result name="input" type="tiles">pages.searchUsuario</result>
			<result type="tiles">pages.searchUsuario</result>
			<result name="noUser" type="tiles">pages.nouser</result>
		</action>

		<action name="adminAltaUsuario" class="gestorUsuarios" method="saveNew">
			<result name="input" type="tiles">pages.createUsuario</result>
			<result type="tiles">pages.consUsuario</result>
			<result name="noUser" type="tiles">pages.nouser</result>
		</action>

		<action name="adminActualizarUsuario" class="gestorUsuarios"
			method="save">
			<result name="input" type="tiles">pages.mantUsuario</result>
			<result type="tiles">pages.consUsuario</result>
			<result name="noUser" type="tiles">pages.nouser</result>
		</action>

		<action name="adminBorrarUsuario" class="gestorUsuarios"
			method="delete">
			<result type="tiles">pages.searchUsuario</result>
			<result name="noUser" type="tiles">pages.nouser</result>
		</action>

<!-- 		<action name="adminGrupos" class="gestorGrupos" method="newSearch"> -->
<!-- 			<result type="tiles">pages.searchGrupo</result> -->
<!-- 			<result name="noUser" type="tiles">pages.nouser</result> -->
<!-- 		</action> -->

<!-- 		<action name="adminNuevoGrupo" class="gestorGrupos" method="create"> -->
<!-- 			<result type="tiles">pages.createGrupo</result> -->
<!-- 			<result name="noUser" type="tiles">pages.nouser</result> -->
<!-- 		</action> -->

<!-- 		<action name="adminEditarGrupo" class="gestorGrupos" method="edit"> -->
<!-- 			<result type="tiles">pages.mantGrupo</result> -->
<!-- 			<result name="noUser" type="tiles">pages.nouser</result> -->
<!-- 		</action> -->

<!-- 		<action name="adminVerGrupo" class="gestorGrupos" method="edit"> -->
<!-- 			<result type="tiles">pages.consGrupo</result> -->
<!-- 			<result name="noUser" type="tiles">pages.nouser</result> -->
<!-- 		</action> -->

<!-- 		<action name="adminBuscarGrupos" class="gestorGrupos" method="search"> -->
<!-- 			<result name="input" type="tiles">pages.searchGrupo</result> -->
<!-- 			<result type="tiles">pages.searchGrupo</result> -->
<!-- 			<result name="noUser" type="tiles">pages.nouser</result> -->
<!-- 		</action> -->

<!-- 		<action name="adminAltaGrupo" class="gestorGrupos" method="saveNew"> -->
<!-- 			<result name="input" type="tiles">pages.createGrupo</result> -->
<!-- 			<result type="tiles">pages.consGrupo</result> -->
<!-- 			<result name="noUser" type="tiles">pages.nouser</result> -->
<!-- 		</action> -->

<!-- 		<action name="adminActualizarGrupo" class="gestorGrupos" -->
<!-- 			method="save"> -->
<!-- 			<result name="input" type="tiles">pages.mantGrupo</result> -->
<!-- 			<result type="tiles">pages.consGrupo</result> -->
<!-- 			<result name="noUser" type="tiles">pages.nouser</result> -->
<!-- 		</action> -->

<!-- 		<action name="adminBorrarGrupo" class="gestorGrupos" method="delete"> -->
<!-- 			<result type="tiles">pages.searchGrupo</result> -->
<!-- 			<result name="noUser" type="tiles">pages.nouser</result> -->
<!-- 		</action> -->
		<!-- menu configuracion -->
		<action name="manageOrganismo">
			<result type="tiles">pages.config.Organismos.search</result>
			<result name="noUser" type="tiles">pages.nouser</result>
		</action>

<!-- 		<action name="buscarOrganismo" class="organismoAction"> -->
<!-- 			<result type="tiles">pages.config.Organismos.search</result> -->
<!-- 			<result name="noUser" type="tiles">pages.nouser</result> -->
<!-- 		</action> -->

		<!-- <action name="nuevoOrganismoOLD">
			<result type="tiles">pages.config.Organismos.nuevo</result>
			<result name="noUser" type="tiles">pages.nouser</result>
		</action>
		<action name="saveOrganismoOLD" class="organismoAction" method="create">
			<result name="input" type="tiles">pages.config.Organismos.nuevo
			</result>
			<result type="tiles">pages.config.Organismos.edit</result>
			<result name="noUser" type="tiles">pages.nouser</result>
		</action>

		<action name="editOrganismoOLD" class="organismoAction" method="load">
			<result type="tiles">pages.config.Organismos.edit</result>
			<result name="noUser" type="tiles">pages.nouser</result>
		</action>

		<action name="updateOrganismoOLD" class="organismoAction" method="update">
			<result name="input" type="tiles">pages.config.Organismos.edit
			</result>
			<result name="noUser" type="tiles">pages.nouser</result>
			<result type="tiles">pages.config.Organismos.edit</result>
		</action>

		<action name="deleteOrganismoOLD" class="organismoAction" method="delete">
			<result type="tiles">pages.config.Organismos.search</result>
			<result name="noUser" type="tiles">pages.nouser</result>
		</action> -->

		<action name="manageUnidadOrg">
			<result type="tiles">pages.config.UnidadesOrgs.search</result>
			<result name="noUser" type="tiles">pages.nouser</result>
		</action>

<!-- 		<action name="buscarUnidadOrg" class="unidadOrganizacionalAction"> -->
<!-- 			<result type="tiles">pages.config.UnidadesOrgs.search</result> -->
<!-- 			<result name="noUser" type="tiles">pages.nouser</result> -->
<!-- 		</action> -->

<!-- 		<action name="nuevoUnidadOrg"> -->
<!-- 			<result type="tiles">pages.config.UnidadesOrgs.nuevo</result> -->
<!-- 			<result name="noUser" type="tiles">pages.nouser</result> -->
<!-- 		</action> -->
<!-- 		<action name="saveUnidadOrg" class="unidadOrganizacionalAction" -->
<!-- 			method="create"> -->
<!-- 			<result name="input" type="tiles">pages.config.UnidadesOrgs.nuevo -->
<!-- 			</result> -->
<!-- 			<result name="noUser" type="tiles">pages.nouser</result> -->
<!-- 			<result name="success" type="tiles">pages.config.UnidadesOrgs.edit</result> -->
			
<!-- 		</action> -->

<!-- 		<action name="editUnidadOrg" class="unidadOrganizacionalAction" -->
<!-- 			method="load"> -->
<!-- 			<result name="noUser" type="tiles">pages.nouser</result> -->
<!-- 			<result name="success"  type="tiles">pages.config.UnidadesOrgs.edit</result> -->
<!-- 		</action> -->

<!-- 		<action name="updateUnidadOrg" class="unidadOrganizacionalAction" -->
<!-- 			method="update"> -->
<!-- 			<result name="input" type="tiles">pages.config.UnidadesOrgs.edit -->
<!-- 			</result> -->
<!-- 			<result name="noUser" type="tiles">pages.nouser</result> -->
<!-- 			<result name="success"  type="tiles">pages.config.UnidadesOrgs.edit</result> -->
<!-- 		</action> -->

<!-- 		<action name="deleteUnidadOrg" class="unidadOrganizacionalAction" -->
<!-- 			method="delete"> -->
<!-- 			<result name="noUser" type="tiles">pages.nouser</result> -->
<!-- 			<result name="success"  type="tiles">pages.config.UnidadesOrgs.search</result> -->
<!-- 		</action> -->


		<!-- Menu info usuario -->
		<action name="infoUsuario">
			<result name="noUser" type="tiles">pages.nouser</result>
			<result name="success"  type="tiles">pages.infoUsuario</result>
		</action>

<!-- 		<action name="detallesUsuarioLogado" class="seguridadAction" -->
<!-- 			method="detallesUsuarioLogado"> -->
<!-- 			<result name="noUser" type="tiles">pages.nouser</result> -->
<!-- 			<result name="success"  type="tiles">pages.infoUsuario</result> -->
<!-- 		</action> -->

<!-- 		<action name="metodoProtegido"> -->
<!-- 			<result name="noUser" type="tiles">pages.nouser</result> -->
<!-- 			<result name="success"  type="tiles">pages.metodoProtegido</result> -->
<!-- 		</action> -->

<!-- 		<action name="resultadoMetodoProtegido" class="seguridadAction" -->
<!-- 			method="ejecutarMetodoProtegido"> -->
<!-- 			<result name="noUser" type="tiles">pages.nouser</result> -->
<!-- 			<result name="success"  type="tiles">pages.metodoProtegidoOK</result> -->
<!-- 		</action> -->

<!-- 		<action name="manageAuditoria"> -->
<!-- 			<result name="noUser" type="tiles">pages.nouser</result> -->
<!-- 			<result name="success"  type="tiles">pages.Auditoria.manage</result> -->
<!-- 		</action> -->
		<action name="buscarAuditoria" class="auditoriaAction">
			<result name="noUser" type="tiles">pages.nouser</result>
			<result name="success"  type="tiles">pages.Auditoria.manage</result>
			
		</action>

		<!-- Menu descarga archivos -->
		<action name="infoDescargaArchivos">
			<result name="noUser" type="tiles">pages.nouser</result>
			<result name="success"  type="tiles">pages.descarga.ficheros</result>
		</action>

		<action name="descargarFichero" class="gestorDescargaFicheros"
			method="descargarFichero">
			<result name="noUser" type="tiles">pages.nouser</result>
			<result name="input" type="tiles">pages.descarga.ficheros</result>
		</action>

		<!-- Menu informes 
		
		<action name="infoInforme" class="generadorInformesAction"
			method="nuevoInforme">
			<result name="noUser" type="tiles">pages.nouser</result>
			<result name="success"  type="tiles">pages.informes.info</result>
		</action>

		<action name="generarInforme" class="generadorInformesAction"
			method="generateReport">
			<result name="input" type="tiles">pages.informes.info</result>
			<result type="jasper">site.index.page</result>
			<result name="noUser" type="tiles">pages.nouser</result>
		
		</action>
-->
		<!-- Menu Ajax -->
		<action name="infoAjax">
			<result name="noUser" type="tiles">pages.nouser</result>
			<result name="success"  type="tiles">pages.ajax.info</result>
		</action>
<!-- 
		<action name="ejemploAjax" class="ejemploAjaxAction" method="execute">
			<result name="input" type="tiles">pages.ajax.info</result>
			<result name="success" type="json">
				<param name="noCache">true</param>
			</result>
			<result name="noUser" type="tiles">pages.nouser</result>
			
		</action>
 -->
<!-- 		<action name="comboAjax" class="combosAjaxAction" method="execute"> -->
<!-- 			<result name="input" type="tiles">pages.ajax.combos</result> -->
<!-- 			<result name="noUser" type="tiles">pages.nouser</result> -->
			
<!-- 		</action> -->
<!--
		<action name="combosJSON" class="combosAjaxAction" method="getJSON">
			<result name="success" type="json">
				<param name="noCache">true</param>
			</result>
			<result name="noUser" type="tiles">pages.nouser</result>
		
		</action>
	-->	
<!-- 		<action name="formsAjax" class="formsAjaxAction" method="execute"> -->
<!-- 			<result name="input" type="tiles">pages.ajax.forms</result> -->
<!-- 		</action> -->
<!--		
		<action name="formsJSON" class="formsAjaxAction" method="getJSON">
			<result name="success" type="json">
				<param name="noCache">true</param>
			</result>
		</action>
		
		<action name="catalogJSON" class="catalogAction" method="getJSON">
			<result name="success" type="json">
				<param name="noCache">true</param>
				<param name="excludeProperties">
					catalogService
				</param>
			</result>
			<result name="error" type="json">
				<param name="noCache">true</param>
				<param name="excludeProperties">
					catalogService
				</param>
			</result>
		</action>
		
		<action name="enlacesAjax" class="formsAjaxAction" method="execute">
			<result name="input" type="tiles">pages.ajax.enlaces</result>
		</action>
	-->	
		<!-- Menu afirma -->
		<action name="firmaForm">
			<result name="noUser" type="tiles">pages.nouser</result>
			<result name="success"  type="tiles">pages.afirma.firmaForm</result>
		</action>

		<action name="firmaFichero">
			<result name="noUser" type="tiles">pages.nouser</result>
			<result name="success"  type="tiles">pages.afirma.firmaFichero</result>
		</action>

		<!-- <action name="firmaWebJSON" class="firmaWebAction">
			<result name="success" type="json">
				<param name="noCache">true</param>
				<param name="excludeProperties">
					servicio,firmaUsuario,nombre,apellidos
				</param>
			</result>
			<result name="error" type="json">
				<param name="noCache">true</param>
				<param name="excludeProperties">
					servicio,firmaUsuario,nombre,apellidos
				</param>
			</result>
		</action> -->

		<!-- <action name="instaladorAFirma" class="firmaWebAction" method="registraFirma">
			<result type="tiles">pages.afirma.firmaWeb</result>
		</action>
		-->
	  <!-- ************************************* -->
	  <!-- 	PLATAFORMA MENSAJERIA - SERVIDORES	 -->
	  <!-- ************************************* -->
		
<!-- 
		<action name="adminServidores" class="servidoresAction" method="newSearch">
			<result type="tiles">pages.searchServidor</result>
		</action>
-->		

		<action name="checkSMTPConnection" class="servidoresAction" method="checkSMTPConnection">
			<result  name="success" type="redirectAction"> <!-- *se usa* -->
				<param name="actionName">editServidor</param>
				<param name="parse">true</param>
				<param name="idServidor">${idServidor}</param>
			</result>
		</action>		

		<action name="buscarServidores" class="servidoresAction"
			method="search"><!-- *se usa* -->
			<result name="noUser" type="tiles">pages.nouser</result>
			<result name="success" type="tiles">pages.searchServidor</result>

		</action>
		<action name="editServidor" class="servidoresAction" method="load"><!-- *se usa* -->

			<result name="noUser" type="tiles">pages.nouser</result>
			<result name="success"  type="tiles">pages.servidor.edit</result>
		</action>
		<action name="updateServidor" class="servidoresAction" method="update"><!-- *se usa* -->
			<result name="success" type="redirectAction">
				<param name="actionName">editServidor</param>
				<param name="parse">true</param> 
				<param name="idServidor">${servidor.servidorid}</param>
			</result>
			<result name="noUser" type="tiles">pages.nouser</result>
		

		</action>
		<action name="deleteServidor" class="servidoresAction" method="delete"><!-- *se usa* -->
			<result type="redirectAction">
				<param name="actionName">buscarServidores</param>
			</result>
			<result name="noUser" type="tiles">pages.nouser</result>
			
		</action>
		<action name="deleteServidoresSeleccionados" class="servidoresAction"
			method="deleteSelected"><!-- *se usa* -->
			<result type="redirectAction">
				<param name="actionName">buscarServidores</param>
			</result>
			<result name="noUser" type="tiles">pages.nouser</result>
			
		</action>

		<action name="nuevoServidor" class="servidoresAction"><!-- *se usa* -->
			<result name="noUser" type="tiles">pages.nouser</result>
			<result name="success"  type="tiles">pages.servidor.create</result>
		</action>
		
		<action name="saveServidor" class="servidoresAction" method="create"><!-- *se usa* -->
			<result name="error" type="tiles">pages.servidor.create</result>
			<result  name="success" type="redirectAction"> 
				<param name="actionName">editServidor</param>
				<param name="parse">true</param>
				<param name="idServidor">${idServidor}</param>
			</result>
			<result name="noUser" type="tiles">pages.nouser</result>	
		</action>
		
		<action name="addParametroServidor" class="servidoresAction"
			method="addParametroServidor"><!-- *se usa* -->
			<result name="error" type="redirectAction">
				<param name="actionName">editServidor</param>
				<param name="parse">true</param> 
				<param name="idServidor">${parametroServidor.servidorid}</param>
				<param name="parametroServidor.tipoParametroId">${parametroServidor.tipoparametroid}</param>
				<param name="parametroServidor.valor">${parametroServidor.valor}</param>
			</result>
			<result name="success" type="redirectAction">
				<param name="actionName">editServidor</param>
				<param name="parse">true</param> 
				<param name="idServidor">${parametroServidor.servidorid}</param>
			</result>
			<result name="noUser" type="tiles">pages.nouser</result>	
		</action>
		
		<action name="deleteParametroServidor" class="servidoresAction"
			method="deleteParametroServidor"><!-- *se usa* -->
			<result name="success" type="redirectAction">
				<param name="actionName">editServidor</param>
				<param name="parse">true</param> 
				<param name="idServidor">${idServidor}</param>
			</result>
			<result name="noUser" type="tiles">pages.nouser</result>
		</action>
		
		<action name="addPlanificacion" class="servidoresAction"
			method="addPlanificacion"><!-- *se usa* -->
			<result name="error" type="redirectAction">
				<param name="actionName">editServidor</param>
				<param name="parse">true</param>
				<param name="idServidor">${planificacionServidor.servidorId}</param>
				<param name="planificacionServidor.lunes">${planificacionServidor.lunes}</param>
				<param name="planificacionServidor.martes">${planificacionServidor.martes}</param>
				<param name="planificacionServidor.miercoles">${planificacionServidor.miercoles}</param>
				<param name="planificacionServidor.jueves">${planificacionServidor.jueves}</param>
				<param name="planificacionServidor.viernes">${planificacionServidor.viernes}</param>
				<param name="planificacionServidor.sabado">${planificacionServidor.sabado}</param>
				<param name="planificacionServidor.domingo">${planificacionServidor.domingo}</param>
				<param name="planificacionServidor.horaDesde">${planificacionServidor.horaDesde}</param>
				<param name="planificacionServidor.horaHasta">${planificacionServidor.horaHasta}</param>
			</result>
			<result name="success" type="redirectAction">
				<param name="actionName">editServidor</param>
				<param name="parse">true</param> 
				<param name="idServidor">${planificacionServidor.servidorId}</param>	
			</result>
			<result name="noUser" type="tiles">pages.nouser</result>
		</action>
		
		<action name="deletePlanificacionServidor" class="servidoresAction"
			method="deletePlanificacionServidor"><!-- *se usa* -->
			<result name="success" type="redirectAction">
				<param name="actionName">editServidor</param>
				<param name="parse">true</param> 
				<param name="idServidor">${idServidor}</param>
			</result>
			<result name="noUser" type="tiles">pages.nouser</result>
			
		</action>

		<!-- ************************************* -->
		<!--FIN PLATAFORMA MENSAJERIA - SERVIDORES -->
		<!-- ************************************* -->
		<!-- ************************************* -->
		<!-- PLATAFORMA MENSAJERIA - PROVEEDORESSMS -->
		<!-- ************************************* -->

		<action name="buscarProveedorSMS" class="proveedorSMSAction"
			method="search"><!-- *se usa* -->
			<result name="noUser" type="tiles">pages.nouser</result>
			<result name="success"  type="tiles">pages.searchProveedorSMS</result>
		</action>
		
		<action name="editProveedorSMS" class="proveedorSMSAction"
			method="load"><!-- *se usa* -->
			<result name="noUser" type="tiles">pages.nouser</result>
			<result name="success"  type="tiles">pages.proveedorSMS.edit</result>
		</action>
		
		<action name="updateProveedorSMS" class="proveedorSMSAction"
			method="update"><!-- *se usa* -->
			<interceptor-ref name="storeStack" />
			<result name="success" type="redirectAction">
				<param name="actionName">editProveedorSMS</param>
				<param name="parse">true</param> 
				<param name="idProveedorSMS">${proveedorSMS.proveedorSMSId}</param>
			</result>
			<result name="noUser" type="tiles">pages.nouser</result>
		</action>
		
		<action name="deleteProveedorSMS" class="proveedorSMSAction"
			method="delete"><!-- *se usa* -->
			<result type="redirectAction">
				<param name="actionName">buscarProveedorSMS</param>
			</result>
			<result name="noUser" type="tiles">pages.nouser</result>			
		</action>
		
		<action name="deleteProveedoresSMSSeleccionados" class="proveedorSMSAction"
			method="deleteSelected"><!-- *se usa* -->
			<result type="redirectAction">
				<param name="actionName">buscarProveedorSMS</param>
			</result>
			<result name="noUser" type="tiles">pages.nouser</result>
		</action>

		<action name="nuevoProveedorSMS" class="proveedorSMSAction"><!-- *se usa* -->
			<result name="noUser" type="tiles">pages.nouser</result>
			<result name="success"  type="tiles">pages.proveedorSMS.create</result>
		</action>
		<action name="saveProveedorSMS" class="proveedorSMSAction"
			method="create"><!-- *se usa* -->
			<result name="error" type="tiles">pages.proveedorSMS.create</result>
			<result name="success" type="redirectAction">
				<param name="actionName">editProveedorSMS</param>
				<param name="parse">true</param> 
				<param name="idProveedorSMS">${idProveedorSMS}</param>
			</result>
			<result name="noUser" type="tiles">pages.nouser</result>
		</action>
		
		<action name="addParametroProveedorSMS" class="proveedorSMSAction"
			method="addParametroProveedorSMS"><!-- *se usa* -->
			<result name="success" type="redirectAction">
				<param name="actionName">editProveedorSMS</param>
				<param name="parse">true</param> 
				<param name="idProveedorSMS">${parametroServidor.servidorid}</param>
			</result>
			<result name="noUser" type="tiles">pages.nouser</result>
			<result name="error" type="redirectAction">
				<param name="actionName">editProveedorSMS</param>
				<param name="parse">true</param> 
				<param name="idProveedorSMS">${parametroServidor.servidorid}</param>
				<param name="parametroServidor.tipoParametroId">${parametroServidor.tipoparametroId}</param>
				<param name="parametroServidor.valor">${parametroServidor.valor}</param>
			</result>
		</action>
		
		<action name="deleteParametroProveedorSMS" class="proveedorSMSAction"
			method="deleteParametroProveedorSMS"><!-- *se usa* -->
			<result name="success" type="redirectAction">
				<param name="actionName">editProveedorSMS</param>
				<param name="parse">true</param> 
				<param name="idProveedorSMS">${idProveedorSMS}</param>
			</result>
			<result name="noUser" type="tiles">pages.nouser</result>
		</action>
		
		<action name="addPlanificacionProveedorSMS" class="proveedorSMSAction"
			method="addPlanificacionProveedorSMS"><!-- *se usa* -->
			<result name="success" type="redirectAction">
				<param name="actionName">editProveedorSMS</param>
				<param name="parse">true</param> 
				<param name="idProveedorSMS">${planificacionServidor.servidorId}</param>
			</result>
			<result name="noUser" type="tiles">pages.nouser</result>
			<result name="error" type="redirectAction">
				<param name="actionName">editProveedorSMS</param>
				<param name="parse">true</param>
				<param name="idProveedorSMS">${planificacionServidor.servidorId}</param>
				<param name="planificacionServidor.lunes">${planificacionServidor.lunes}</param>
				<param name="planificacionServidor.martes">${planificacionServidor.martes}</param>
				<param name="planificacionServidor.miercoles">${planificacionServidor.miercoles}</param>
				<param name="planificacionServidor.jueves">${planificacionServidor.jueves}</param>
				<param name="planificacionServidor.viernes">${planificacionServidor.viernes}</param>
				<param name="planificacionServidor.sabado">${planificacionServidor.sabado}</param>
				<param name="planificacionServidor.domingo">${planificacionServidor.domingo}</param>
				<param name="planificacionServidor.horaDesde">${planificacionServidor.horaDesde}</param>
				<param name="planificacionServidor.horaHasta">${planificacionServidor.horaHasta}</param>
			</result>
		</action>
		<action name="deletePlanificacionProveedorSMS" class="proveedorSMSAction"
			method="deletePlanificacionProveedorSMS"><!-- *se usa* -->
			<result name="success" type="redirectAction">
				<param name="actionName">editProveedorSMS</param>
				<param name="parse">true</param> 
				<param name="idProveedorSMS">${idProveedorSMS}</param>
			</result>
			<result name="noUser" type="tiles">pages.nouser</result>
		
		</action>
		<!-- ************************************* -->
		<!--FIN PLATAFORMA MENSAJERIA - PROVEEDORSMS -->
		<!-- ************************************* -->
		<!-- ************************************* -->
		<!-- PLATAFORMA MENSAJERIA - RECEPTORESSMS -->
		<!-- ************************************* -->
		<action name="buscarReceptorSMS" class="receptorSMSAction"
			method="search"><!-- *se usa* -->
			<result name="noUser" type="tiles">pages.nouser</result>
			<result name="success"  type="tiles">pages.searchReceptorSMS</result>
		</action>
		
		<action name="editReceptorSMS" class="receptorSMSAction"
			method="load"><!-- *se usa* -->
			<result name="noUser" type="tiles">pages.nouser</result>
			<result name="success"  type="tiles">pages.receptorSMS.edit</result>
		</action>
		
		<action name="updateReceptorSMS" class="receptorSMSAction"
			method="update"><!-- *se usa* -->
			<interceptor-ref name="storeStack" />
			<result name="success" type="redirectAction">
				<param name="actionName">editReceptorSMS</param>
				<param name="parse">true</param> 
				<param name="idReceptorSMS">${receptorSMS.receptorSMSId}</param>
			</result>
			<result name="noUser" type="tiles">pages.nouser</result>
		</action>
		
		<action name="deleteReceptorSMS" class="receptorSMSAction"
			method="delete"><!-- *se usa* -->
			<result type="redirectAction">
				<param name="actionName">buscarReceptorSMS</param>
			</result>
			<result name="noUser" type="tiles">pages.nouser</result>	 
		</action>
		
		<action name="deleteReceptoresSMSSeleccionados" class="receptorSMSAction"
			method="deleteSelected"><!-- *se usa* -->
			<result type="redirectAction">
				<param name="actionName">buscarReceptorSMS</param>
			</result>
			<result name="noUser" type="tiles">pages.nouser</result>
		</action>

		<action name="nuevoReceptorSMS" class="receptorSMSAction"><!-- *se usa* -->
			<result name="noUser" type="tiles">pages.nouser</result>
			<result name="success"  type="tiles">pages.receptorSMS.create</result>
		</action>
		
		<action name="saveReceptorSMS" class="receptorSMSAction"
			method="create"><!-- *se usa* -->
			<result name="error" type="tiles">pages.receptorSMS.create</result>
			<result name="success" type="redirectAction">
				<param name="actionName">editReceptorSMS</param>
				<param name="parse">true</param>
				<param name="idReceptorSMS">${idReceptorSMS}</param>
			</result>
			<result name="noUser" type="tiles">pages.nouser</result>
		</action>
		
		<action name="addParametroReceptorSMS" class="receptorSMSAction"
			method="addParametroReceptorSMS"><!-- *se usa* -->
			<result name="success" type="redirectAction">
				<param name="actionName">editReceptorSMS</param>
				<param name="parse">true</param> 
				<param name="idReceptorSMS">${parametroServidor.servidorid}</param>
			</result>
			<result name="noUser" type="tiles">pages.nouser</result>
			<result name="error" type="redirectAction">
				<param name="actionName">editReceptorSMS</param>
				<param name="parse">true</param> 
				<param name="idReceptorSMS">${parametroServidor.servidorid}</param>
				<param name="parametroServidor.tipoParametroId">${parametroServidor.tipoparametroid}</param>
				<param name="parametroServidor.valor">${parametroServidor.valor}</param>
			</result>
		</action>
		
		<action name="deleteParametroReceptorSMS" class="receptorSMSAction"
			method="deleteParametroReceptorSMS"><!-- *se usa* -->
			<result name="success" type="redirectAction">
				<param name="actionName">editReceptorSMS</param>
				<param name="parse">true</param> 
				<param name="idReceptorSMS">${idReceptorSMS}</param>
			</result>
			<result name="noUser" type="tiles">pages.nouser</result>
		</action>
		
		<action name="addPlanificacionReceptorSMS" class="receptorSMSAction"
			method="addPlanificacionReceptorSMS"><!-- *se usa* -->
			<result name="success" type="redirectAction">
				<param name="actionName">editReceptorSMS</param>
				<param name="parse">true</param> 
				<param name="idReceptorSMS">${planificacionServidor.servidorId}</param>
			</result>
			<result name="noUser" type="tiles">pages.nouser</result>
			<result name="error" type="redirectAction">
				<param name="actionName">editReceptorSMS</param>
				<param name="parse">true</param>
				<param name="idReceptorSMS">${planificacionServidor.servidorId}</param>
				<param name="planificacionServidor.lunes">${planificacionServidor.lunes}</param>
				<param name="planificacionServidor.martes">${planificacionServidor.martes}</param>
				<param name="planificacionServidor.miercoles">${planificacionServidor.miercoles}</param>
				<param name="planificacionServidor.jueves">${planificacionServidor.jueves}</param>
				<param name="planificacionServidor.viernes">${planificacionServidor.viernes}</param>
				<param name="planificacionServidor.sabado">${planificacionServidor.sabado}</param>
				<param name="planificacionServidor.domingo">${planificacionServidor.domingo}</param>
				<param name="planificacionServidor.horaDesde">${planificacionServidor.horaDesde}</param>
				<param name="planificacionServidor.horaHasta">${planificacionServidor.horaHasta}</param>
			</result>
		</action>
		
		<action name="deletePlanificacionReceptorSMS" class="receptorSMSAction"
			method="deletePlanificacionReceptorSMS"><!-- *se usa* -->
			<result name="success" type="redirectAction">
				<param name="actionName">editReceptorSMS</param>
				<param name="parse">true</param> 
				<param name="idReceptorSMS">${idReceptorSMS}</param>
			</result>
			<result name="noUser" type="tiles">pages.nouser</result>
		</action>
		<!-- ***************************************** -->
		<!-- FIN PLATAFORMA MENSAJERIA - RECEPTORESSMS -->
		<!-- ***************************************** -->
		<!-- ************************************** -->
		<!-- PLATAFORMA MENSAJERIA - SERVIDORESPUSH -->
		<!-- ************************************** -->
		<action name="buscarServidorPush" class="servidorPushAction"
			method="search"><!-- *se usa* -->
			<result name="noUser" type="tiles">pages.nouser</result>
			<result name="success"  type="tiles">pages.searchServidorPush</result>
		</action>
		
		<action name="editServidorPush" class="servidorPushAction"
			method="load"><!-- *se usa* -->
			<result name="noUser" type="tiles">pages.nouser</result>
			<result name="success"  type="tiles">pages.servidorPush.edit</result>
		</action>
		
		<action name="updateServidorPush" class="servidorPushAction"
			method="update"><!-- *se usa* -->
			<interceptor-ref name="storeStack" />
			<result name="success" type="redirectAction">
				<param name="actionName">editServidorPush</param>
				<param name="parse">true</param> 
				<param name="idServidorPush">${servidorPush.servidorPushId}</param>
			</result>
			<result name="noUser" type="tiles">pages.nouser</result>
		</action>
		
		<action name="deleteServidorPush" class="servidorPushAction"
			method="delete"><!-- *se usa* -->
			<result name="noUser" type="tiles">pages.nouser</result>
			<result name="success"  type="redirectAction">
				<param name="actionName">buscarServidorPush</param>
			</result>	
		</action>
		
		<action name="deleteServidoresPushSeleccionados" class="servidorPushAction"
			method="deleteSelected"><!-- *se usa* -->
			<result name="noUser" type="tiles">pages.nouser</result>
			<result name="success"  type="redirectAction">
				<param name="actionName">buscarServidorPush</param>
			</result>
		</action>

		<action name="nuevoServidorPush" class="servidorPushAction"><!-- *se usa* -->
			<result name="noUser" type="tiles">pages.nouser</result>
			<result name="success"  type="tiles">pages.servidorPush.create</result>
		</action>
		
		<action name="saveServidorPush" class="servidorPushAction"
			method="create"><!-- *se usa* -->
			<result name="error" type="tiles">pages.servidorPush.create</result>
			<result name="success" type="redirectAction">
				<param name="actionName">editServidorPush</param>
				<param name="parse">true</param> 
				<param name="idServidorPush">${idServidorPush}</param>
			</result>
			<result name="noUser" type="tiles">pages.nouser</result>
		</action>
		
		<action name="addParametroServidorPush" class="servidorPushAction"
			method="addParametroServidorPush"><!-- *se usa* -->
			<result name="success" type="redirectAction">
				<param name="actionName">editServidorPush</param>
				<param name="parse">true</param> 
				<param name="idServidorPush">${parametroServidor.servidorid}</param>
			</result>
			<result name="noUser" type="tiles">pages.nouser</result>	
			<result name="error" type="redirectAction">
				<param name="actionName">editServidorPush</param>
				<param name="parse">true</param> 
				<param name="idServidorPush">${parametroServidor.servidorid}</param>
				<param name="parametroServidor.tipoParametroId">${parametroServidor.tipoparametroid}</param>
				<param name="parametroServidor.valor">${parametroServidor.valor}</param>
			</result>
		</action>
		
		<action name="deleteParametroServidorPush" class="servidorPushAction"
			method="deleteParametroServidorPush"><!-- *se usa* -->
			<result name="success" type="redirectAction">
				<param name="actionName">editServidorPush</param>
				<param name="parse">true</param> 
				<param name="idServidorPush">${idServidorPush}</param>
			</result>
			<result name="noUser" type="tiles">pages.nouser</result>			
		</action>
		
		<action name="addPlanificacionServidorPush" class="servidorPushAction"
			method="addPlanificacionServidorPush"><!-- *se usa* -->
			<result name="success" type="redirectAction">
				<param name="actionName">editServidorPush</param>
				<param name="parse">true</param> 
				<param name="idServidorPush">${planificacionServidor.servidorId}</param>
			</result>
			<result name="noUser" type="tiles">pages.nouser</result>		
			<result name="error" type="redirectAction">
				<param name="actionName">editServidorPush</param>
				<param name="parse">true</param>
				<param name="idServidorPush">${planificacionServidor.servidorId}</param>
				<param name="planificacionServidor.lunes">${planificacionServidor.lunes}</param>
				<param name="planificacionServidor.martes">${planificacionServidor.martes}</param>
				<param name="planificacionServidor.miercoles">${planificacionServidor.miercoles}</param>
				<param name="planificacionServidor.jueves">${planificacionServidor.jueves}</param>
				<param name="planificacionServidor.viernes">${planificacionServidor.viernes}</param>
				<param name="planificacionServidor.sabado">${planificacionServidor.sabado}</param>
				<param name="planificacionServidor.domingo">${planificacionServidor.domingo}</param>
				<param name="planificacionServidor.horaDesde">${planificacionServidor.horaDesde}</param>
				<param name="planificacionServidor.horaHasta">${planificacionServidor.horaHasta}</param>
			</result>
		</action>
		
		<action name="deletePlanificacionServidorPush" class="servidorPushAction"
			method="deletePlanificacionServidorPush"><!-- *se usa* -->
			<result name="success" type="redirectAction">
				<param name="actionName">editServidorPush</param>
				<param name="parse">true</param> 
				<param name="idServidorPush">${idServidorPush}</param>
			</result>
			<result name="noUser" type="tiles">pages.nouser</result>		
		</action>
		
		<!-- ******************************************* -->
		<!-- FIN PLATAFORMA MENSAJERIA - SERVIDORESPUSH -->
		<!-- ****************************************** -->
		<!-- ************************************* -->
		<!-- PLATAFORMA MENSAJERIA - APLICACIONES -->
		<!-- ************************************* -->
		<action name="buscarAplicaciones" class="aplicacionAction"
			method="search"><!-- *se usa* -->
			<result name="noUser" type="tiles">pages.nouser</result>
			<result name="success" type="tiles">pages.searchAplicacion</result>
		</action>
		<action name="editAplicacion" class="aplicacionAction" method="load"><!-- *se usa* -->
			<result name="noUser" type="tiles">pages.nouser</result>
			<result name="success" type="tiles">pages.aplicacion.edit</result>
		</action>
		<action name="updateAplicacion" class="aplicacionAction"
			method="update"><!-- *se usa* -->
			<result name="success" type="redirectAction">
				<param name="actionName">editAplicacion</param>
				<param name="parse">true</param> 
				<param name="idAplicacion">${aplicacion.aplicacionId}</param>
			</result>
			<result name="noUser" type="tiles">pages.nouser</result>

		</action>
		<action name="deleteAplicacion" class="aplicacionAction"
			method="delete"><!-- *se usa* -->
			<result name="success" type="redirectAction">
				<param name="actionName">buscarAplicaciones</param>
			</result>
			<result name="noUser" type="tiles">pages.nouser</result>
		</action>
		<action name="deleteAplicacionesSeleccionadas" class="aplicacionAction"
			method="deleteSelected"><!-- *se usa* -->
			<result name="success" type="redirectAction">
				<param name="actionName">buscarAplicaciones</param>
			</result>
			<result name="noUser" type="tiles">pages.nouser</result>
		</action>

		<action name="nuevaAplicacion" class="aplicacionAction"><!-- *se usa* -->
			<result name="success" type="tiles">pages.aplicacion.create</result>
			<result name="noUser" type="tiles">pages.nouser</result>
		</action>
		<action name="saveAplicacion" class="aplicacionAction" method="create"><!-- *se usa* -->
			<result name="error" type="tiles">pages.aplicacion.create</result>
			<result name="noUser" type="tiles">pages.nouser</result>
			<result name="success" type="redirectAction">
				<param name="actionName">editAplicacion</param>
				<param name="parse">true</param> 
				<param name="idAplicacion">${idAplicacion}</param>
			</result>
		</action>
		<action name="viewAplicacion" class="aplicacionAction" method="loadDetalleAplicacion">
			<result name="success" type="tiles">pages.aplicacion.detalle</result>
			<result name="noUser" type="tiles">pages.nouser</result>
		</action>
		<action name="loadPlanificacionesApp" class="aplicacionAction"
			method="loadPlanificaciones">
			<result name="success" type="tiles">pages.aplicacion.editplanificacionapp
			</result>
			<result name="noUser" type="tiles">pages.nouser</result>
		</action>
		<action name="loadPlanificacionesServ" class="aplicacionAction"
			method="loadPlanificaciones">
			<result name="success" type="tiles">pages.aplicacion.editplanificacionserv
			</result>
			<result name="noUser" type="tiles">pages.nouser</result>
		</action>
		<action name="loadPlanificacionesServer" class="aplicacionAction"
			method="loadPlanificaciones">
			<result name="success" type="tiles">pages.aplicacion.editplanificacionserver
			</result>
			<result name="noUser" type="tiles">pages.nouser</result>
		</action>
		<action name="loadPlanificacionesProveedorSMS" class="aplicacionAction"
			method="loadPlanificaciones">
			<result name="success" type="tiles">pages.aplicacion.editplanificacionproveedorsms
			</result>
			<result name="noUser" type="tiles">pages.nouser</result>
		</action>
		<action name="loadPlanificacionesReceptorSMS" class="aplicacionAction"
			method="loadPlanificaciones">
			<result name="success" type="tiles">pages.aplicacion.editplanificacionreceptorsms
			</result>
			<result name="noUser" type="tiles">pages.nouser</result>
		</action>
		<action name="loadPlanificacionesServidorPush" class="aplicacionAction"
			method="loadPlanificaciones">
			<result name="success" type="tiles">pages.aplicacion.editplanificacionservidorpush
			</result>
			<result name="noUser" type="tiles">pages.nouser</result>
		</action>
		<action name="loadPlanificacionesOrganismo" class="aplicacionAction"
			method="loadPlanificaciones">
			<result name="success" type="tiles">pages.aplicacion.editplanificacionorganismos
			</result>
			<result name="noUser" type="tiles">pages.nouser</result>
		</action>


		<!-- ************************************* -->
		<!-- PLATAFORMA MENSAJERIA - SERVICIOS -->
		<!-- ************************************* -->
		<!-- ************************************* -->
		<!-- PLATAFORMA MENSAJERIA - SERVICIOS -->
		<!-- ************************************* -->
		<action name="ajaxLoadServicios" class="serviciosAction"
			method="ajaxLoadServicios">
			<result name="success">/uploadOK.jsp</result>
			<result name="noUser" type="tiles">pages.nouser</result>
			
		</action>
		
		<action name="buscarServicios" class="serviciosAction" method="searchServicios">
			<result name="noUser" type="tiles">pages.nouser</result>
			<result name="success"  type="tiles">pages.searchServicios</result>
		</action>
		<action name="editServicio" class="serviciosAction" method="load">
			<result name="noUser" type="tiles">pages.nouser</result>
			<result name="success"  type="tiles">pages.servicio.edit</result>
		</action>
		<action name="updateServicio" class="serviciosAction" method="update">
			<result name="success" type="redirectAction">
				<param name="actionName">editServicio</param>
				<param name="parse">true</param> 
				<param name="idServicio">${idServicio}</param>
			</result>
			<result name="noUser" type="tiles">pages.nouser</result>
			 
		</action>
		<action name="deleteServicio" class="serviciosAction" method="delete">
			<result name="noUser" type="tiles">pages.nouser</result>
			<result name="success"  type="redirectAction">
				<param name="actionName">buscarServicios</param>
			</result>
		</action>
		<action name="deleteServicioAplicacion" class="serviciosAction"
			method="deleteServicioAplicacion">
			<result name="success" type="redirectAction">
				<param name="actionName">editAplicacion</param>
				<param name="parse">true</param> 
				<param name="idAplicacion">${idAplicacion}</param>
			</result>
			<result name="noUser" type="tiles">pages.nouser</result>
			
		</action>

		<action name="deleteServiciosAplicacionSeleccionados" class="serviciosAction"
			method="deleteServicioAplicacionSelected">
			<result name="success" type="redirectAction">
				<param name="actionName">editAplicacion</param>
				<param name="parse">true</param> 
				<param name="idAplicacion">${idAplicacion}</param>
			</result>
			<result name="noUser" type="tiles">pages.nouser</result>
		</action>

		<action name="deleteServiciosSeleccionados" class="serviciosAction"
			method="deleteSelected">
			<result name="noUser" type="tiles">pages.nouser</result>
			<result name="success"  type="redirectAction">
				<param name="actionName">buscarServicios</param>
			</result>
		</action>
		<action name="nuevoServicio" class="serviciosAction">
			<result name="noUser" type="tiles">pages.nouser</result>
			<result name="success"  type="tiles">pages.servicio.create</result>
		</action>
		<action name="saveServicio" class="serviciosAction" method="create">
			<result name="error" type="tiles">pages.servicio.create</result>
			<result name="success" type="redirectAction">
				<param name="actionName">editServicio</param>
				<param name="parse">true</param> 
				<param name="idServicio">${idServicio}</param>
			</result>
			<result name="noUser" type="tiles">pages.nouser</result>
		
		</action>
		
		<action name="aplicacionSelectEvent" class="serviciosAction" method="aplicacionSelectEvent">
			<result name="success" type="tiles">pages.servicio.create</result>		
		</action>
		<action name="aplicacionSelectEditEvent" class="serviciosAction" method="aplicacionSelectEvent">
			<result name="success" type="tiles">pages.servicio.edit</result>		
		</action>
		<action name="activarMultiorganismoSelectEditEvent" class="serviciosAction" method="activarMultiorganismoSelectEvent">
			<result name="success" type="tiles">pages.servicio.edit</result>		
		</action>
	<!--  	<action name="activarMultiorganismoSelectEditEvent" class="serviciosAction" method="activarMultiorganismoSelectEvent">
			<result name="success" type="tiles"></result>		
		</action>-->
				
		<action name="nuevoServicioAplicacion" class="serviciosAction">
			<result name="noUser" type="tiles">pages.nouser</result>
			<result name="success"  type="tiles">pages.servicioAplicacion.create</result>
		</action>
		<action name="saveServicioAplicacion" class="serviciosAction"
			method="createServicioAplicacion">
			<result name="error" type="tiles">pages.servicioAplicacion.create
			</result>
			<result name="success" type="redirectAction">
				<param name="actionName">editServicioAplicacion</param>
				<param name="parse">true</param> 
				<param name="idServicio">${idServicio}</param>
			</result>
			<result name="noUser" type="tiles">pages.nouser</result>
			
		</action>
		<action name="editServicioAplicacion" class="serviciosAction"
			method="load">
			<result name="noUser" type="tiles">pages.nouser</result>
			<result name="success"  type="tiles">pages.servicioAplicacion.edit</result>
		</action>
		<action name="updateServicioAplicacion" class="serviciosAction"
			method="updateServicioAplicacion">
			<result name="success" type="redirectAction">
				<param name="actionName">editServicioAplicacion</param>
				<param name="parse">true</param> 
				<param name="idServicio">${idServicio}</param>
			</result>
			<result name="noUser" type="tiles">pages.nouser</result>
		
		</action>
		<action name="deletePlanificacionesServidorSelected" class="serviciosAction"
			method="deletePlanificacionesSelected">
			<result name="success" type="redirectAction">
				<param name="actionName">editServicio</param>
				<param name="parse">true</param> 
				<param name="idServicio">${idServicio}</param>
			</result>
			<result name="noUser" type="tiles">pages.nouser</result>
			
		</action>
		<action name="deleteServidorServiciosSelected" class="serviciosAction"
			method="deleteServidoresServiciosSelected">
			<result name="success" type="redirectAction">
				<param name="actionName">editServicio</param>
				<param name="parse">true</param> 
				<param name="idServicio">${idServicio}</param>
			</result>
			<result name="noUser" type="tiles">pages.nouser</result>
			
		</action>
		<action name="deleteServicioOrganismosSelected" class="serviciosAction"
			method="deleteServicioOrganismosSelected">
			<result name="success" type="redirectAction">
				<param name="actionName">editServicio</param>
				<param name="parse">true</param> 
				<param name="idServicio">${idServicio}</param>
			</result>
			<result name="noUser" type="tiles">pages.nouser</result>
			
		</action>
		<action name="deleteServidorServicio" class="serviciosAction"
			method="deleteServidorServicio">
			<result name="success" type="redirectAction">
				<param name="actionName">editServicio</param>
				<param name="parse">true</param>
				<param name="idServicio">${idServicio}</param>
			</result>
		</action>
		<action name="deleteServicioOrganismo" class="serviciosAction"
			method="deleteServicioOrganismo">
			<result name="success" type="redirectAction">
				<param name="actionName">editServicio</param>
				<param name="parse">true</param>
				<param name="idServicio">${idServicio}</param>
			</result>
		</action>
		<action name="addServidorServicio" class="serviciosAction"
			method="addServidorServicio">
			<result name="error" type="redirectAction">
				<param name="actionName">editServicio</param>
				<param name="parse">true</param> 
				<param name="idServicio">${idServicio}</param>
				<param name="servidorServicio.servidorId">${servidorServicio.servidorId}</param>
				<param name="servidorServicio.numIntentos">${servidorServicio.numIntentos}</param>
				<param name="servidorServicio.headerSMS">${servidorServicio.headerSMS}</param>
				<param name="servidorServicio.proveedorUsuarioSMS">${servidorServicio.proveedorUsuarioSMS}</param>
				<param name="servidorServicio.proveedorPasswordSMS">${servidorServicio.proveedorPasswordSMS}</param>
			</result>		
			<result name="success" type="redirectAction">
				<param name="actionName">editServicio</param>
				<param name="parse">true</param> 
				<param name="idServicio">${idServicio}</param>
			</result>
			<result name="noUser" type="tiles">pages.nouser</result>
			
		</action>
		<action name="addServicioOrganismos" class="serviciosAction"
			method="addServicioOrganismos">
			<result name="error" type="redirectAction">
				<param name="actionName">editServicio</param>
				<param name="parse">true</param> 
				<param name="idServicio">${idServicio}</param>
				
			</result>		
			
			<result name="noUser" type="tiles">pages.nouser</result>
			
		</action>
		<action name="deletePlanificacionServicio" class="serviciosAction"
			method="deletePlanificacionServicio">
			<result name="success" type="redirectAction">
				<param name="actionName">editServicio</param>
				<param name="parse">true</param> 
				<param name="idServicio">${idServicio}</param>
			</result>
			<result name="noUser" type="tiles">pages.nouser</result>
			
		</action>
		<action name="addPlanificacionServicio" class="serviciosAction"
			method="addPlanificacionServicio">
			<result name="error" type="redirectAction">
				<param name="actionName">editServicio</param>
				<param name="parse">true</param>
				<param name="idServicio">${planificacionServidor.servicioId}</param>
				<param name="planificacionServidor.lunes">${planificacionServidor.lunes}</param>
				<param name="planificacionServidor.martes">${planificacionServidor.martes}</param>
				<param name="planificacionServidor.miercoles">${planificacionServidor.miercoles}</param>
				<param name="planificacionServidor.jueves">${planificacionServidor.jueves}</param>
				<param name="planificacionServidor.viernes">${planificacionServidor.viernes}</param>
				<param name="planificacionServidor.sabado">${planificacionServidor.sabado}</param>
				<param name="planificacionServidor.domingo">${planificacionServidor.domingo}</param>
				<param name="planificacionServidor.horaDesde">${planificacionServidor.horaDesde}</param>
				<param name="planificacionServidor.horaHasta">${planificacionServidor.horaHasta}</param>
				<param name="planificacionServidor.servidorId">${planificacionServidor.servidorId}</param>
			</result>
			<result name="success" type="redirectAction">
				<param name="actionName">editServicio</param>
				<param name="parse">true</param> 
				<param name="idServicio">${planificacionServidor.servicioId}</param>
				
			</result>
			<result name="noUser" type="tiles">pages.nouser</result>
			
		</action>

		<!-- ************************************* -->
		<!-- PLATAFORMA MENSAJERIA - PLANIFICACIONES -->
		<!-- ************************************* -->
		<action name="buscarPlanificaciones" class="planificacionAction"
			method="search">
			<result name="noUser" type="tiles">pages.nouser</result>
			<result name="success"  type="tiles">pages.searchPlanificacion</result>
		</action>
		<action name="editPlanificacion" class="planificacionAction"
			method="load">
			<result name="noUser" type="tiles">pages.nouser</result>
			<result name="success"  type="tiles">pages.planificacion.edit</result>
		</action>
		<action name="updatePlanificacionServ" class="planificacionAction"
			method="updatePlanificacionServicio">
			<result name="success" type="redirectAction">
				<param name="actionName">editServicio</param>
				<param name="parse">true</param> 
				<param name="idServicio">${idServicio}</param>
			</result>
			<result name="error" type="redirectAction">
				<param name="actionName">editServicio</param>
				<param name="parse">true</param> 
				<param name="idServicio">${idServicio}</param>
			</result>
			<result name="noUser" type="tiles">pages.nouser</result>
			
		</action>
		<action name="updatePlanificacionOrganismo" class="planificacionAction"
			method="updatePlanificacionOrganismo">
			<result name="success" type="redirectAction">
				<param name="actionName">editOrganismo</param>
				<param name="parse">true</param> 
				<param name="idOrganismo">${idOrganismo}</param>
			</result>
			<result name="error" type="redirectAction">
				<param name="actionName">editOrganismo</param>
				<param name="parse">true</param> 
				<param name="idOrganismo">${idOrganismo}</param>
			</result>
			<result name="noUser" type="tiles">pages.nouser</result>
			
		</action>
		<action name="updatePlanificacionServer" class="planificacionAction"
			method="updatePlanificacionServer">
			<result name="success" type="redirectAction">
				<param name="actionName">editServidor</param>
				<param name="parse">true</param> 
				<param name="idServidor">${idServidor}</param>
			</result>
			<result name="noUser" type="tiles">pages.nouser</result>
			
			<result name="error" type="redirectAction">
				<param name="actionName">editServidor</param>
				<param name="parse">true</param> 
				<param name="idServidor">${idServidor}</param>
			</result>			
		</action>
		<action name="updatePlanificacionProveedorSMS" class="planificacionAction"
			method="updatePlanificacionServer">
			<result name="success" type="redirectAction">
				<param name="actionName">editProveedorSMS</param>
				<param name="parse">true</param> 
				<param name="idProveedorSMS">${idProveedorSMS}</param>
			</result>
			<result name="noUser" type="tiles">pages.nouser</result>
		
			<result name="error" type="redirectAction">
				<param name="actionName">editProveedorSMS</param>
				<param name="parse">true</param> 
				<param name="idProveedorSMS">${idProveedorSMS}</param>
			</result>
		</action>
		<action name="updatePlanificacionReceptorSMS" class="planificacionAction"
			method="updatePlanificacionServer">
			<result name="success" type="redirectAction">
				<param name="actionName">editReceptorSMS</param>
				<param name="parse">true</param> 
				<param name="idReceptorSMS">${idReceptorSMS}</param>
			</result>
			<result name="noUser" type="tiles">pages.nouser</result>
			
			<result name="error" type="redirectAction">
				<param name="actionName">editReceptorSMS</param>
				<param name="parse">true</param> 
				<param name="idReceptorSMS">${idReceptorSMS}</param>
			</result>			
		</action>
		<action name="updatePlanificacionServidorPush" class="planificacionAction"
			method="updatePlanificacionServer">
			<result name="success" type="redirectAction">
				<param name="actionName">editServidorPush</param>
				<param name="parse">true</param> 
				<param name="idServidorPush">${idServidorPush}</param>
			</result>
			<result name="noUser" type="tiles">pages.nouser</result>
		
			<result name="error" type="redirectAction">
				<param name="actionName">editServidorPush</param>
				<param name="parse">true</param> 
				<param name="idServidorPush">${idServidorPush}</param>
			</result>
		</action>

		<action name="updatePlanificacion" class="planificacionAction"
			method="updatePlanificacionServicio">
			<result name="error" type="redirectAction">
				<param name="actionName">editPlanificacion</param>
				<param name="parse">true</param> 
				<param name="idPlanificacion">${idPlanificacion}</param>
				<param name="nAction">${nAction}</param>
			</result>
			<result name="noUser" type="tiles">pages.nouser</result>
			
			<result name="success" type="redirectAction">
				<param name="actionName">editPlanificacion</param>
				<param name="parse">true</param> 
				<param name="idPlanificacion">${idPlanificacion}</param>
				<param name="nAction">${nAction}</param>
			</result>
		</action>
		<action name="deletePlanificacion" class="planificacionAction"
			method="delete">
			<result name="noUser" type="tiles">pages.nouser</result>
			<result name="success"  type="redirectAction">
				<param name="actionName">buscarPlanificaciones</param>
			</result>
		</action>
		<action name="deletePlanificacionesSeleccionadas" class="planificacionAction"
			method="deleteSelected">
			<result name="noUser" type="tiles">pages.nouser</result>
			<result name="success"  type="redirectAction">
				<param name="actionName">buscarPlanificaciones</param>
			</result>
		</action>
		<action name="nuevaPlanificacion" class="planificacionAction">
			<result name="noUser" type="tiles">pages.nouser</result>
			<result name="success"  type="tiles">pages.planificacion.create</result>
		</action>
		<action name="nuevaPlanificacionApp" class="planificacionAction">
			<result name="noUser" type="tiles">pages.nouser</result>
			<result name="success"  type="tiles">pages.aplicacion.newplanificacionapp</result>
		</action>
		<action name="savePlanificacionApp" class="planificacionAction"
			method="createPlanificacionApp">
			<result name="error" type="redirectAction">
				<param name="actionName">viewAplicacion</param>
				<param name="parse">true</param> 
				<param name="idAplicacion">${idAplicacion}</param>
			</result>
			<result name="success" type="redirectAction">
				<param name="actionName">viewAplicacion</param>
				<param name="parse">true</param> 
				<param name="idAplicacion">${idAplicacion}</param>
			</result>
			<result name="noUser" type="tiles">pages.nouser</result>
			
		</action>
		<action name="savePlanificacion" class="planificacionAction"
			method="create">
			<result name="error" type="redirectAction">
				<param name="actionName">nuevaPlanificacion</param>
				<param name="parse">true</param>
				<param name="planificacion.servicioId">${planificacion.servicioId}</param>
				<param name="nAction">${nAction}</param>
				<param name="from">${from}</param>
				<param name="idFrom">${idFrom}</param>
				<param name="var">${var}</param>
				<param name="idAplicacion">${idAplicacion}</param>
				<param name="planificacion.lunes">${planificacion.lunes}</param>
				<param name="planificacion.martes">${planificacion.martes}</param>
				<param name="planificacion.miercoles">${planificacion.miercoles}</param>
				<param name="planificacion.jueves">${planificacion.jueves}</param>
				<param name="planificacion.viernes">${planificacion.viernes}</param>
				<param name="planificacion.sabado">${planificacion.sabado}</param>
				<param name="planificacion.domingo">${planificacion.domingo}</param>
				<param name="planificacion.horaDesde">${planificacion.horaDesde}</param>
				<param name="planificacion.horaHasta">${planificacion.horaHasta}</param>
				<param name="planificacion.servidorId">${planificacion.servidorId}</param>				
				<param name="planificacion.activo">${planificacion.activo}</param>
				<param name="planificacion.tipoPlanificacionId">${planificacion.tipoPlanificacionId}</param>
				
			</result>
			<result name="success" type="redirectAction">
				<param name="actionName">editPlanificacion</param>
				<param name="parse">true</param> 
				<param name="idPlanificacion">${idPlanificacion}</param>
				<param name="nAction">updatePlanificacion</param>
			</result>
			<result name="noUser" type="tiles">pages.nouser</result>
			
		</action>
		<action name="savePlanificacionViewApp" class="planificacionAction"
			method="createPlanificacionApp">
			<!-- <result name="error" type="tiles">pages.planificacion.create</result> -->
			<result name="error" type="redirectAction">
				<param name="actionName">viewAplicacion</param>
				<param name="parse">true</param> 
				<param name="idAplicacion">${idAplicacion}</param>
			</result>
			<result name="success" type="redirectAction">
				<param name="actionName">viewAplicacion</param>
				<param name="parse">true</param> 
				<param name="idAplicacion">${idAplicacion}</param>
			</result>
			<result name="noUser" type="tiles">pages.nouser</result>
			
		</action>

		<action name="deletePlanificacionServicioViewApp" class="planificacionAction"
			method="delete">
			<result name="success" type="redirectAction">
				<param name="actionName">viewAplicacion</param>
				<param name="idAplicacion">${idAplicacion}</param>
			</result>
			<result name="noUser" type="tiles">pages.nouser</result>
	
		</action>

		<action name="updatePlanificacionViewApp" class="planificacionAction"
			method="updatePlanificacionViewApp">
			<result name="error" type="redirectAction">
				<param name="actionName">viewAplicacion</param>
				<param name="parse">true</param> 
				<param name="idAplicacion">${idAplicacion}</param>
			</result>	
			<result name="success" type="redirectAction">
				<param name="actionName">viewAplicacion</param>
				<param name="parse">true</param> 
				<param name="idAplicacion">${idAplicacion}</param>
			</result>
			
		</action>
		<action name="loadServiroresByTipoPlan" class="planificacionAction"
			method="loadServidoresByTipoPlan">
			<result name="noUser" type="tiles">pages.nouser</result>
			<result name="success"  type="tiles">pages.planificacion.loadComboServidor
			</result>
		</action>
		<action name="loadTipoPlanificacionByServicioCanal" class="planificacionAction"
			method="loadTipoPlanificacionByServicioCanal">
			<result name="noUser" type="tiles">pages.nouser</result>
			<result name="success" type="tiles">pages.planificacion.loadComboTipoPlanificacion
			</result>
		</action>


		<!-- ************************************* -->
		<!-- PLATAFORMA MENSAJERIA - USUARIOS -->
		<!-- ************************************* -->
		<action name="buscarUsuarios" class="usuarioAction" method="search">
			<result name="noUser" type="tiles">pages.nouser</result>
			<result name="success" type="tiles">pages.searchUsuariosPlt</result>
		</action>
		<action name="editUsuario" class="usuarioAction" method="load">
			<result name="noUser" type="tiles">pages.nouser</result>
			<result name="success"  type="tiles">pages.usuario.edit</result>
		</action>
		<action name="updateUsuario" class="usuarioAction" method="update">
			<result name="noUser" type="tiles">pages.nouser</result>
			<result name="success" type="redirectAction">
				<param name="actionName">editUsuario</param>
				<param name="parse">true</param> 
				<param name="idUsuario">${idUsuario}</param>
			</result>
		</action>
		<action name="deleteUsuario" class="usuarioAction" method="delete">
			<result name="noUser" type="tiles">pages.nouser</result>
			<result name="success"  type="redirectAction">
				<param name="actionName">buscarUsuarios</param>
			</result>
		</action>
		<action name="deleteUsuariosSeleccionados" class="usuarioAction"
			method="deleteSelected">
			<result name="noUser" type="tiles">pages.nouser</result>
			<result name="success"  type="redirectAction">
				<param name="actionName">buscarUsuarios</param>
			</result>
		</action>
		<action name="nuevoUsuario" class="usuarioAction">
			<result name="noUser" type="tiles">pages.nouser</result>
			<result name="success"  type="tiles">pages.usuario.create</result>
		</action>
		<action name="saveUsuario" class="usuarioAction" method="create">
			<result name="error" type="tiles">pages.usuario.create</result>
			<result name="noUser" type="tiles">pages.nouser</result>
			<result name="success" type="redirectAction">
				<param name="actionName">editUsuario</param>
				<param name="parse">true</param> 
				<param name="idUsuario">${idUsuario}</param>
			</result>
		</action>
		<action name="addUsuarioAplicacion" class="usuarioAction"
			method="addUsuarioAplicacion">
			<result name="noUser" type="tiles">pages.nouser</result>
			<result name="success" type="redirectAction">
				<param name="actionName">editUsuario</param>
				<param name="parse">true</param> 
				<param name="idUsuario">${idUsuario}</param>
			</result>
		</action>
		<action name="deleteUsuarioAplicacion" class="usuarioAction"
			method="deleteUsuarioAplicacion">
			<result name="noUser" type="tiles">pages.nouser</result>
			<result name="success" type="redirectAction">
				<param name="actionName">editUsuario</param>
				<param name="parse">true</param> 
				<param name="idUsuario">${idUsuario}</param>
			</result>
		</action>
		<action name="loadUserByName" class="usuarioAction" method="loadUserByName">
			<result name="noUser" type="tiles">pages.nouser</result>
			<result name="success" type="redirectAction">
				<param name="actionName">nuevoUsuario</param>
				<param name="parse">true</param>
				<param name="usuario.nombre">${usuario.nombre}</param>
				<param name="usuario.email">${usuario.email}</param>
				<param name="usuario.login">${usuario.login}</param>
			</result>
		</action>
		<action name="loadUserByNameEdit" class="usuarioAction" method="loadUserByName">
			<result name="noUser" type="tiles">pages.nouser</result>
			<result name="success" type="redirectAction">
				<param name="actionName">editUsuario</param>
				<param name="parse">true</param>
				<param name="usuario.nombre">${usuario.nombre}</param>
				<param name="usuario.email">${usuario.email}</param>
				<param name="usuario.login">${usuario.login}</param>
				<param name="idUsuario">${idUsuario}</param>
				<param name="nombreLDAP">${nombreLDAP}</param>
				<param name="emailLDAP">${emailLDAP}</param>
			</result>
		</action>
		<!-- ************************************* -->
		<!-- PLATAFORMA MENSAJERIA - ESTADISTICAS -->
		<!-- ************************************* -->
		<action name="buscarEstadisticas" class="estadisticaAction"
			method="search"><!-- method="search" -->
			<result name="noUser" type="tiles">pages.nouser</result>
			<result name="success" type="tiles">pages.estadisticas</result>
			<result name="error" type="tiles">pages.nouser</result>
		</action>
		<!-- ************************************* -->
		<!-- PLATAFORMA MENSAJERIA - AUDITORIA -->
		<!-- ************************************* -->
		<action name="buscarAuditoriasPlataforma" class="auditoriaPlataforma"
			method="newSearch">
			<result name="noUser" type="tiles">pages.nouser</result>
			<result name="success" type="tiles">pages.auditoriaPlataforma</result>
		</action>
		<action name="listAuditoriasPlataforma" class="auditoriaPlataforma"
			method="search"><!-- method="search" -->
			<result name="noUser" type="tiles">pages.nouser</result>
			<result name="success" type="tiles">pages.auditoriaPlataforma</result>
		</action>
		<!-- ************************************* -->
		<!-- PLATAFORMA MENSAJERIA - USUARIOS PUSH -->
		<!-- ************************************* -->
		<action name="buscarUsuariosPush" class="usuariosPushAction"
			method="newSearch">
			<result name="noUser" type="tiles">pages.nouser</result>
			<result name="success" type="tiles">pages.usuariosPush</result>
		</action>
		<action name="listUsuariosPush" class="usuariosPushAction"
			method="search">
			<result name="noUser" type="tiles">pages.nouser</result>
			<result name="success" type="tiles">pages.usuariosPush</result>
		</action>
		
		<!-- *************************************** -->
		<!-- PGINA DE PERMISO DENEGADO -->
		<action name="permisoDenegado" class="usuarioAction">
			<result name="noUser" type="tiles">pages.nouser</result>
			<result name="success" type="tiles">pages.permisoDenegado</result>
		</action>
		<!-- *************************************** -->
		<!--        GESTION ENVIOS					 -->
		<!-- *************************************** -->

		<action name="buscarGestionEnvios" class="gestionEnvioAction"
			method="newSearch"><!-- method="search" -->
			<result name="noUser" type="tiles">pages.nouser</result>
			<result name="success" type="tiles">pages.gestionEnvios</result>
		</action>
		<action name="listGestionEnvios" class="gestionEnvioAction"
			method="search"><!-- method="search" -->
			<result name="noUser" type="tiles">pages.nouser</result>
			<result name="success" type="tiles">pages.gestionEnvios</result>
			
		</action>
		<action name="viewLote" class="gestionEnvioAction" method="loadLote">
			<result name="noUser" type="tiles">pages.nouser</result>
			<result name="success" type="tiles">pages.gestionEnvios.viewLote</result>

		</action>
		
		<action name="viewMensajeGeneral" class="gestionEnvioAction" method="loadMsj">
			<result name="noUser" type="tiles">pages.nouser</result>
			<result name="success" type="tiles">pages.gestionEnvios.viewMensajeGeneral</result>
		</action>

		<action name="viewMensaje" class="gestionEnvioAction" method="loadMensaje">
			<result name="noUser" type="tiles">pages.nouser</result>
			<result name="success" type="tiles">pages.gestionEnvios.viewEmail
			</result>
		</action>
		<action name="viewMensajeSMS" class="gestionEnvioAction"
			method="loadMensaje">
			<result name="noUser" type="tiles">pages.nouser</result>
			<result name="success" type="tiles">pages.gestionEnvios.viewSMS
			</result>
		</action>
		<action name="viewHistorico" class="gestionEnvioAction"
			method="loadHistoricoMsj">
			<result name="noUser" type="tiles">pages.nouser</result>
			<result name="success" type="tiles">pages.gestionEnvios.viewHistoricoMensaje
			</result>
		</action>
		<action name="viewMensajeNotificacionPush" class="gestionEnvioAction"
			method="loadMensaje">
			<result name="noUser" type="tiles">pages.nouser</result>
			<result name="success" type="tiles">pages.gestionEnvios.viewNotificacionPush
			</result>
		</action>
		<action name="viewContent" class="gestionEnvioAction" method="loadContenidoMensaje">
			<result name="noUser" type="tiles">pages.nouser</result>
			<result name="success" type="tiles">pages.gestionEnvios.viewContent
			</result>
		</action>
		<action name="accionSeleccionados" class="gestionEnvioAction"
			method="accionSeleccionados">
			<result name="noUser" type="tiles">pages.nouser</result>
			<result name="success" type="redirectAction">
					<param name="actionName">listGestionEnvios</param>
					<param name="parse">true</param> 
  					<param name="gestionEnvioBean.aplicacionId">${gestionEnvioBean.aplicacionId}</param>
  					<param name="gestionEnvioBean.servicioId">${gestionEnvioBean.servicioId}</param>
  					<param name="gestionEnvioBean.canalId">${gestionEnvioBean.canalId}</param>
  					<param name="gestionEnvioBean.servidorId">${gestionEnvioBean.servidorId}</param>
  					<param name="gestionEnvioBean.email">${gestionEnvioBean.email}</param>
  					<param name="gestionEnvioBean.estadoId">${gestionEnvioBean.estadoId}</param>
  					<param name="gestionEnvioBean.telefonoMovil">${gestionEnvioBean.telefonoMovil}</param>
  					<param name="gestionEnvioBean.fechaDesde">${gestionEnvioBean.fechaDesde}</param>
  					<param name="gestionEnvioBean.fechaHasta">${gestionEnvioBean.fechaHasta}</param>
  					<param name="gestionEnvioBean.idLote">${gestionEnvioBean.idLote}</param>
  					
  					
			</result>
		</action>
		<action name="downloadAdjunto" class="gestionEnvioAction"
			method="loadAdjunto">
			<result name="noUser" type="tiles">pages.nouser</result>
			<result name="success" type="stream">
				<param name="contentType">application/octet-stream</param>
				<param name="inputName">fileInputStream</param>
				<param name="contentDisposition">${adjuntoDescargable}</param>
				<param name="bufferSize">1024</param>
			</result>
		</action>

		<!-- *************************************** -->
		<!-- GESTION ENVIOS HISTORICOS -->
		<!-- *************************************** -->

		<action name="buscarGestionEnviosHistoricos" class="gestionEnvioHistoricoAction"
			method="newSearch"><!-- method="search" -->
			<result name="noUser" type="tiles">pages.nouser</result>
			<result name="success" type="tiles">pages.gestionEnviosHistoricos
			</result>
		</action>
		<action name="listGestionEnviosHistoricos" class="gestionEnvioHistoricoAction"
			method="search"><!-- method="search" -->
			<result name="noUser" type="tiles">pages.nouser</result>
			<result name="success" type="tiles">pages.gestionEnviosHistoricos
			</result>
		</action>
		<action name="viewLoteHistorico" class="gestionEnvioHistoricoAction" method="loadLote">
			<result name="noUser" type="tiles">pages.nouser</result>
			<result name="success" type="tiles">pages.gestionEnvios.viewLoteHistoricos</result>

		</action>
		<action name="viewMensajeHistorico" class="gestionEnvioHistoricoAction"
			method="loadMensaje">
			<result name="noUser" type="tiles">pages.nouser</result>
			<result name="success" type="tiles">pages.gestionEnviosHistoricos.viewEmail
			</result>
		</action>
		<action name="viewMensajeSMSHistorico" class="gestionEnvioHistoricoAction"
			method="loadMensaje">
			<result name="noUser" type="tiles">pages.nouser</result>
			<result name="success" type="tiles">pages.gestionEnviosHistoricos.viewSMS
			</result>
		</action>
		<action name="viewMensajeNotificacionPushHistorico" class="gestionEnvioHistoricoAction"
			method="loadMensaje">
			<result name="noUser" type="tiles">pages.nouser</result>
			<result name="success" type="tiles">pages.gestionEnviosHistoricos.viewNotificacionPush
			</result>
		</action>
		<action name="viewHistoricoHist" class="gestionEnvioHistoricoAction"
			method="loadHistoricoMsj">
			<result name="noUser" type="tiles">pages.nouser</result>
			<result name="success" type="tiles">pages.gestionEnviosHistoricos.viewHistoricoMensaje
			</result>
		</action>
		<action name="viewContentHistorico" class="gestionEnvioHistoricoAction"
			method="loadContenidoMensaje">
			<result name="noUser" type="tiles">pages.nouser</result>
			<result name="success" type="tiles">pages.gestionEnviosHistoricos.viewContent
			</result>
		</action>
		<action name="accionSeleccionadosHistorico" class="gestionEnvioHistoricoAction"
			method="accionSeleccionados">
			<result name="noUser" type="tiles">pages.nouser</result>
			<result name="success" type="redirectAction">
					<param name="actionName">listGestionEnviosHistoricos</param>
					<param name="parse">true</param> 
  					<param name="gestionEnvioHistoricoBean.aplicacionId">${gestionEnvioHistoricoBean.aplicacionId}</param>
  					<param name="gestionEnvioHistoricoBean.servicioId">${gestionEnvioHistoricoBean.servicioId}</param>
  					<param name="gestionEnvioHistoricoBean.canalId">${gestionEnvioHistoricoBean.canalId}</param>
  					<param name="gestionEnvioHistoricoBean.servidorId">${gestionEnvioHistoricoBean.servidorId}</param>
  					<param name="gestionEnvioHistoricoBean.email">${gestionEnvioHistoricoBean.email}</param>
  					<param name="gestionEnvioHistoricoBean.estadoId">${gestionEnvioHistoricoBean.estadoId}</param>
  					<param name="gestionEnvioHistoricoBean.telefonoMovil">${gestionEnvioHistoricoBean.telefonoMovil}</param>
  					<param name="gestionEnvioHistoricoBean.fechaDesde">${gestionEnvioHistoricoBean.fechaDesde}</param>
  					<param name="gestionEnvioHistoricoBean.fechaHasta">${gestionEnvioHistoricoBean.fechaHasta}</param>
  					<param name="gestionEnvioHistoricoBean.idLote">${gestionEnvioHistoricoBean.idLote}</param>
  					
  					
			</result>
		</action>
		<action name="downloadAdjuntoHistorico" class="gestionEnvioHistoricoAction"
			method="loadAdjunto">
			<result name="noUser" type="tiles">pages.nouser</result>
			<result name="success" type="stream">
				<param name="contentType">application/octet-stream</param>
				<param name="inputName">fileInputStream</param>
				<param name="contentDisposition">${adjuntoDescargable}</param>
				<param name="bufferSize">1024</param>
			</result>
		</action>

		<!-- ************************************* -->
		<!-- PLATAFORMA MENSAJERIA - ORGNISMOS -->
		<!-- ************************************* -->
		<!-- ************************************* -->
		<!-- PLATAFORMA MENSAJERIA - ORGANISMOS -->
		<!-- ************************************* -->
		<action name="buscarOrganismos" class="organismosAction"
			method="search">
			<result name="noUser" type="tiles">pages.nouser</result>
			<result name="success" type="tiles">pages.searchOrganismo</result>
		</action>
		<action name="editOrganismo" class="organismosAction" method="load">
			<result name="noUser" type="tiles">pages.nouser</result>
			<result name="success" type="tiles">pages.organismo.edit</result>
		</action>
		<action name="updateOrganismo" class="organismosAction"
			method="update">
			<result name="success" type="redirectAction">
				<param name="actionName">editOrganismo</param>
				<param name="parse">true</param> 
				<param name="idOrganismo">${organismo.organismoId}</param>
			</result>
			<result name="noUser" type="tiles">pages.nouser</result>

		</action>
		<action name="deleteOrganismo" class="organismosAction"
			method="delete">
			<result name="success" type="redirectAction">
				<param name="actionName">buscarOrganismos</param>
			</result>
			<result name="noUser" type="tiles">pages.nouser</result>
		</action>
		<action name="deleteOrganismosSeleccionados" class="organismosAction"
			method="deleteSelected">
			<result name="success" type="redirectAction">
				<param name="actionName">buscarOrganismos</param>
			</result>
			<result name="noUser" type="tiles">pages.nouser</result>
		</action>

		<action name="nuevoOrganismo" class="organismosAction">
			<result name="success" type="tiles">pages.organismo.create</result>
			<result name="noUser" type="tiles">pages.nouser</result>
		</action>
		<action name="salveOrganismo" class="organismosAction" method="create">
			<result name="error" type="tiles">pages.organismo.create</result>
			<result name="noUser" type="tiles">pages.nouser</result>
			<result name="success" type="redirectAction">
				<param name="actionName">editOrganismo</param>
				<param name="parse">true</param> 
				<param name="idOrganismo">${idOrganismo}</param>
			</result>
		</action>
		<action name="viewOrganismo" class="organismosAction" method="loadDetalleOrganismo">
			<result name="success" type="tiles">pages.organismo.detalle</result>
			<result name="noUser" type="tiles">pages.nouser</result>
		</action>
		<action name="addOrganismoServicios" class="organismosAction"
			method="addOrganismoServicios">
			<result name="error" type="redirectAction">
				<param name="actionName">editOrganismo</param>
				<param name="parse">true</param> 
				<param name="idOrganismo">${idOrganismo}</param>
				
			</result>		
			<result name="noUser" type="tiles">pages.nouser</result>
			
		</action>
		<action name="deleteOrganismoServicio" class="organismosAction"
			method="deleteOrganismoServicio">
			<result name="success" type="redirectAction">
				<param name="actionName">editOrganismo</param>
				<param name="parse">true</param>
				<param name="idOrganismo">${idOrganismo}</param>
			</result>
		</action>
		<action name="servicioSelectEditEvent" class="organismosAction" method="servicioSelectEvent">
			<result name="success" type="tiles">pages.organismo.edit</result>		
		</action>
		<action name="addServidorOrganismo" class="organismosAction"
			method="addServidorOrganismo">
			<result name="error" type="redirectAction">
				<param name="actionName">editOrganismo</param>
				<param name="parse">true</param> 
				<param name="idOrganismo">${idOrganismo}</param>
				
			</result>		
			<result name="noUser" type="tiles">pages.nouser</result>
			
		</action>
		<action name="deleteServidorOrganismo" class="organismosAction"
			method="deleteServidorOrganismo">
			<result name="success" type="redirectAction">
				<param name="actionName">editOrganismo</param>
				<param name="parse">true</param>
				<param name="idOrganismo">${idOrganismo}</param>
			</result>
		</action>
		<action name="addPlanificacionOrganismo" class="organismosAction"
			method="addPlanificacionOrganismo">
			<result name="error" type="redirectAction">
				<param name="actionName">editOrganismo</param>
				<param name="parse">true</param>
				<param name="idOrganismo">${idOrganismo}</param>
				<param name="planificacionOrganismo">${planificacionOrganismo.lunes}</param>
				<param name="planificacionOrganismo">${planificacionOrganismo.martes}</param>
				<param name="planificacionOrganismo">${planificacionOrganismo.miercoles}</param>
				<param name="planificacionOrganismo">${planificacionOrganismo.jueves}</param>
				<param name="planificacionOrganismo">${planificacionOrganismo.viernes}</param>
				<param name="planificacionOrganismo">${planificacionOrganismo.sabado}</param>
				<param name="planificacionOrganismo">${planificacionOrganismo.domingo}</param>
				<param name="planificacionOrganismo">${planificacionOrganismo.horaDesde}</param>
				<param name="planificacionOrganismo">${planificacionOrganismo.horaHasta}</param>
				<param name="planificacionOrganismo">${planificacionOrganismo.servidorId}</param>
			</result>
			<result name="success" type="redirectAction">
				<param name="actionName">editOrganismo</param>
				<param name="parse">true</param> 
				<param name="idOrganismo">${idOrganismo}</param>
				
			</result>
			
			<result name="noUser" type="tiles">pages.nouser</result>
			
		</action>
		<action name="deletePlanificacionOrganismo" class="organismosAction"
			method="deletePlanificacionOrganismo">
			<result name="success" type="redirectAction">
				<param name="actionName">editOrganismo</param>
				<param name="parse">true</param> 
				<param name="idOrganismo">${idOrganismo}</param>
			</result>
			<result name="noUser" type="tiles">pages.nouser</result>
			
		</action>
		<action name="deleteOrganismoServicioSelected" class="organismosAction"
			method="deleteOrganismoServicioSelected">
			<result name="success" type="redirectAction">
				<param name="actionName">editOrganismo</param>
				<param name="parse">true</param> 
				<param name="idOrganismo">${idOrganismo}</param>
			</result>
			<result name="noUser" type="tiles">pages.nouser</result>
			
		</action>
		<action name="deleteServidorOrganismosSelected" class="organismosAction"
			method="deleteServidorOrganismosSelected">
			<result name="success" type="redirectAction">
				<param name="actionName">editOrganismo</param>
				<param name="parse">true</param> 
				<param name="idOrganismo">${idOrganismo}</param>
			</result>
			<result name="noUser" type="tiles">pages.nouser</result>
			
		</action>
		<action name="deletePlanificacionesOrganismoSelected" class="organismosAction"
			method="deletePlanificacionesOrganismoSelected">
			<result name="success" type="redirectAction">
				<param name="actionName">editOrganismo</param>
				<param name="parse">true</param> 
				<param name="idOrganismo">${idOrganismo}</param>
			</result>
			<result name="noUser" type="tiles">pages.nouser</result>
			
		</action>
		
		<!-- ************************************* -->
		<!-- PLATAFORMA MENSAJERIA - SERVICIOS MOVILES -->
		<!-- ************************************* -->

		<action name="buscarServiciosMoviles" class="serviciosMovilesAction"
			method="search">
			<result name="noUser" type="tiles">pages.nouser</result>
			<result name="success" type="tiles">pages.searchServicioMovil</result>
		</action>
		<action name="editServicioMovil" class="serviciosMovilesAction" method="load">
			<result name="noUser" type="tiles">pages.nouser</result>
			<result name="success" type="tiles">pages.servicioMovil.edit</result>
		</action>
		<action name="updateServicioMovil" class="serviciosMovilesAction"
			method="update">
			<result name="success" type="redirectAction">
				<param name="actionName">editServicioMovil</param>
				<param name="parse">true</param>
				<param name="idServicioMovil">${servicioMovil.servicioMovilId}</param>
			</result>
			<result name="noUser" type="tiles">pages.nouser</result>
		</action>
		<action name="deleteServicioMovil" class="serviciosMovilesAction"
			method="delete">
			<result name="success" type="redirectAction">
				<param name="actionName">buscarServiciosMoviles</param>
			</result>
			<result name="noUser" type="tiles">pages.nouser</result>
		</action>
		<action name="deleteServiciosMovilesSeleccionados" class="serviciosMovilesAction"
			method="deleteSelected">
			<result name="success" type="redirectAction">
				<param name="actionName">buscarServiciosMoviles</param>
			</result>
			<result name="noUser" type="tiles">pages.nouser</result>
		</action>
		<action name="deleteImagen" class="serviciosMovilesAction"
			method="deleteImagen">
			<result name="success" type="redirectAction">
				<param name="actionName">editServicioMovil</param>
				<param name="parse">true</param>
				<param name="idServicioMovil">${servicioMovil.servicioMovilId}</param>
			</result>
			<result name="noUser" type="tiles">pages.nouser</result>
		</action>
		<action name="nuevoServicioMovil" class="serviciosMovilesAction">
			<result name="success" type="tiles">pages.servicioMovil.create</result>
			<result name="noUser" type="tiles">pages.nouser</result>
		</action>
		<action name="salveServicioMovil" class="serviciosMovilesAction" method="create">
			<result name="error" type="tiles">pages.servicioMovil.create</result>
			<result name="noUser" type="tiles">pages.nouser</result>
			<result name="success" type="redirectAction">
				<param name="actionName">editServicioMovil</param>
				<param name="parse">true</param> 
				<param name="idServicioMovil">${idServicioMovil}</param>
			</result>
		</action>
		<action name="viewServicioMovil" class="ServiciosMovilesAction" method="loadDetalleServicioMovil">
			<result name="success" type="tiles">pages.servicioMovil.detalle</result>
			<result name="noUser" type="tiles">pages.nouser</result>
		</action>
		
		<!-- ************************************* -->
		<!-- PLATAFORMA MENSAJERIA - DECODIFICADOR -->
		<!-- ************************************* -->

		<action name="decodHome" class="decodeAction">
			<result name="success" type="tiles">pages.decode.decode</result>
			<result name="noUser" type="tiles">pages.nouser</result>
		</action>

		<action name="decodificador" class="decodeAction" method="decode">
			<result name="noUser" type="tiles">pages.nouser</result>
			<result name="success" type="tiles">pages.decode.decode</result>
		</action>
		
		<action name="limpiar" class="decodeAction" method="limpiar">
			<result name="noUser" type="tiles">pages.nouser</result>
			<result name="success" type="tiles">pages.decode.decode</result>
		</action>
		
		
		<!-- ************************************* -->
		<!-- PLATAFORMA MENSAJERIA - EjecucionJobAction -->
		<!-- ************************************* -->
		
		<action name="ejecucionJob" class="ejecucionJobAction">
			<result name="success" type="tiles">pages.ejecutarJob</result>
			<result name="noUser" type="tiles">pages.nouser</result>
		</action>
		
		<action name="seleccionarJob" class="ejecucionJobAction" method="seleccionarJobAction">
			<result name="success" type="tiles">pages.ejecutarJob</result>
			<result name="noUser" type="tiles">pages.nouser</result>
		</action>
		
		<action name="cargarServiciosConservacionEvent" class="ejecucionJobAction" method="cargarServiciosConservacionEvent">
			<result name="success" type="tiles">pages.ejecutarJob</result>		
		</action>
		
	</package>

</struts>
